treasury_gov_pandas/__init__.py
treasury_gov_pandas/load.py
treasury_gov_pandas/datasets/auctions_query/load.py
treasury_gov_pandas/datasets/auctions_query/update.py
treasury_gov_pandas/datasets/deposits_withdrawals_operating_cash/load.py
treasury_gov_pandas/datasets/deposits_withdrawals_operating_cash/update.py
treasury_gov_pandas/datasets/mts/mts_table_4/load.py
treasury_gov_pandas/datasets/mts/mts_table_4/update.py
treasury_gov_pandas/datasets/operating_cash_balance/load.py
treasury_gov_pandas/datasets/operating_cash_balance/update.py
treasury_gov_pandas-0.0.7.dist-info/METADATA
treasury_gov_pandas-0.0.7.dist-info/WHEEL
treasury_gov_pandas-0.0.7.dist-info/licenses/LICENSE
treasury_gov_pandas-0.0.7.dist-info/RECORD
