Metadata-Version: 2.3
Name: treasury_gov_pandas
Version: 0.0.7
Summary: Library for downloading treasury.gov datasets.
Project-URL: Homepage, https://github.com/dharmatech/treasury_gov_pandas.py
Project-URL: Issues, https://github.com/dharmatech/treasury_gov_pandas.py/issues
Author-email: Eduardo Cavazos <wayo.cavazos@gmail.com>
License-File: LICENSE
Classifier: License :: OSI Approved :: MIT License
Classifier: Operating System :: OS Independent
Classifier: Programming Language :: Python :: 3
Requires-Python: >=3.8
Requires-Dist: pandas
Requires-Dist: requests
